WaveGliDA/__init__.py
WaveGliDA/__main__.py
WaveGliDA/calculations.py
WaveGliDA/config.py
WaveGliDA/plotly_json.py
WaveGliDA/read_wg_data.py
WaveGliDA/views.py
WaveGliDA/data/.DS_Store
WaveGliDA/static/css/bootstrap-select.min.css
WaveGliDA/static/css/bootstrap-theme.css
WaveGliDA/static/css/bootstrap-theme.css.map
WaveGliDA/static/css/bootstrap-theme.min.css.map
WaveGliDA/static/css/bootstrap.css
WaveGliDA/static/css/bootstrap.css.map
WaveGliDA/static/css/bootstrap.min.css.map
WaveGliDA/static/css/custom.css
WaveGliDA/static/css/dc.min.css
WaveGliDA/static/css/highlight_code.css
WaveGliDA/static/css/plots.css
WaveGliDA/static/fonts/glyphicons-halflings-regular.eot
WaveGliDA/static/fonts/glyphicons-halflings-regular.svg
WaveGliDA/static/fonts/glyphicons-halflings-regular.ttf
WaveGliDA/static/fonts/glyphicons-halflings-regular.woff
WaveGliDA/static/fonts/glyphicons-halflings-regular.woff2
WaveGliDA/static/img/android-chrome-192x192.png
WaveGliDA/static/img/android-chrome-256x256.png
WaveGliDA/static/img/apple-touch-icon.png
WaveGliDA/static/img/browserconfig.xml
WaveGliDA/static/img/favicon-16x16.png
WaveGliDA/static/img/favicon-32x32.png
WaveGliDA/static/img/favicon.ico
WaveGliDA/static/img/manifest.json
WaveGliDA/static/img/mstile-150x150.png
WaveGliDA/static/img/safari-pinned-tab.svg
WaveGliDA/static/js/MathJax.js
WaveGliDA/static/js/app_sockets.js
WaveGliDA/static/js/bootstrap-3.3.7.min.js
WaveGliDA/static/js/bootstrap-select.min.js
WaveGliDA/static/js/d3-4.8.0.min.js
WaveGliDA/static/js/dc.min.js
WaveGliDA/static/js/editablegrid.js
WaveGliDA/static/js/editablegrid_charts.js
WaveGliDA/static/js/editablegrid_charts_ofc.js
WaveGliDA/static/js/editablegrid_editors.js
WaveGliDA/static/js/editablegrid_renderers.js
WaveGliDA/static/js/editablegrid_utils.js
WaveGliDA/static/js/editablegrid_validators.js
WaveGliDA/static/js/jquery-3.2.1.min.js
WaveGliDA/static/js/plotly-1.26.1.min.js
WaveGliDA/static/json/config.json
WaveGliDA-0.2.1.dist-info/DESCRIPTION.rst
WaveGliDA-0.2.1.dist-info/METADATA
WaveGliDA-0.2.1.dist-info/RECORD
WaveGliDA-0.2.1.dist-info/WHEEL
WaveGliDA-0.2.1.dist-info/entry_points.txt
WaveGliDA-0.2.1.dist-info/metadata.json
WaveGliDA-0.2.1.dist-info/top_level.txt
