Metadata-Version: 2.0
Name: WaveGliDA
Version: 0.2.1
Summary: Import and quick plot ocean surface CO2 data from a wave glider
Home-page: http://luke-gregor.github.io
Author: Luke Gregor
Author-email: luke.e.gregor@gmail.com
License: MIT License
Platform: UNKNOWN
Classifier: Development Status :: 3 - Alpha
Classifier: Intended Audience :: Developers
Classifier: Topic :: Software Development :: Build Tools
Classifier: License :: OSI Approved :: MIT License
Classifier: Programming Language :: Python :: 2
Classifier: Programming Language :: Python :: 2.7
Classifier: Programming Language :: Python :: 3
Classifier: Programming Language :: Python :: 3.4
Classifier: Programming Language :: Python :: 3.5
Classifier: Programming Language :: Python :: 3.6
Requires-Dist: Flask
Requires-Dist: Jinja2
Requires-Dist: MarkupSafe
Requires-Dist: PyExcelerate
Requires-Dist: Pygments
Requires-Dist: Werkzeug
Requires-Dist: click
Requires-Dist: itsdangerous
Requires-Dist: numpy
Requires-Dist: pandas
Requires-Dist: python-dateutil
Requires-Dist: pytz
Requires-Dist: seawater
Requires-Dist: six
